toweroffantasy/__init__.py
toweroffantasy/_base_client.py
toweroffantasy/_client.py
toweroffantasy/_compat.py
toweroffantasy/_constants.py
toweroffantasy/_exceptions.py
toweroffantasy/_files.py
toweroffantasy/_models.py
toweroffantasy/_qs.py
toweroffantasy/_resource.py
toweroffantasy/_response.py
toweroffantasy/_streaming.py
toweroffantasy/_types.py
toweroffantasy/_version.py
toweroffantasy/py.typed
toweroffantasy/_utils/__init__.py
toweroffantasy/_utils/_logs.py
toweroffantasy/_utils/_proxy.py
toweroffantasy/_utils/_reflection.py
toweroffantasy/_utils/_resources_proxy.py
toweroffantasy/_utils/_streams.py
toweroffantasy/_utils/_sync.py
toweroffantasy/_utils/_transform.py
toweroffantasy/_utils/_typing.py
toweroffantasy/_utils/_utils.py
toweroffantasy/lib/.keep
toweroffantasy/resources/__init__.py
toweroffantasy/resources/auth.py
toweroffantasy/resources/banners.py
toweroffantasy/resources/gifts.py
toweroffantasy/resources/health.py
toweroffantasy/resources/matrices.py
toweroffantasy/resources/mounts.py
toweroffantasy/resources/ping.py
toweroffantasy/resources/simulacra.py
toweroffantasy/resources/users.py
toweroffantasy/resources/version.py
toweroffantasy/resources/weapons.py
toweroffantasy/types/__init__.py
toweroffantasy/types/assets.py
toweroffantasy/types/auth_change_password_params.py
toweroffantasy/types/auth_login_params.py
toweroffantasy/types/auth_register_params.py
toweroffantasy/types/banner.py
toweroffantasy/types/banner_create_params.py
toweroffantasy/types/banner_list_params.py
toweroffantasy/types/banner_list_response.py
toweroffantasy/types/banner_retrieve_current_response.py
toweroffantasy/types/category.py
toweroffantasy/types/element.py
toweroffantasy/types/gift.py
toweroffantasy/types/gift_list_params.py
toweroffantasy/types/gift_list_response.py
toweroffantasy/types/gift_retrieve_params.py
toweroffantasy/types/health_check_response.py
toweroffantasy/types/imitation_assets.py
toweroffantasy/types/langs_enum.py
toweroffantasy-1.0.0.dist-info/METADATA
toweroffantasy-1.0.0.dist-info/WHEEL
toweroffantasy-1.0.0.dist-info/licenses/LICENSE
toweroffantasy-1.0.0.dist-info/RECORD
